aioredis/__init__.py
aioredis/abc.py
aioredis/connection.py
aioredis/errors.py
aioredis/locks.py
aioredis/log.py
aioredis/parser.py
aioredis/pool.py
aioredis/pubsub.py
aioredis/stream.py
aioredis/util.py
aioredis/commands/__init__.py
aioredis/commands/cluster.py
aioredis/commands/generic.py
aioredis/commands/geo.py
aioredis/commands/hash.py
aioredis/commands/hyperloglog.py
aioredis/commands/list.py
aioredis/commands/pubsub.py
aioredis/commands/scripting.py
aioredis/commands/server.py
aioredis/commands/set.py
aioredis/commands/sorted_set.py
aioredis/commands/streams.py
aioredis/commands/string.py
aioredis/commands/transaction.py
aioredis/sentinel/__init__.py
aioredis/sentinel/commands.py
aioredis/sentinel/pool.py
evo_aioredis-1.3.4.dist-info/LICENSE
evo_aioredis-1.3.4.dist-info/METADATA
evo_aioredis-1.3.4.dist-info/WHEEL
evo_aioredis-1.3.4.dist-info/top_level.txt
evo_aioredis-1.3.4.dist-info/RECORD
